dagster_plus_cli/__init__.py
dagster_plus_cli-0.0.1.dist-info/LICENSE.md
dagster_plus_cli-0.0.1.dist-info/METADATA
dagster_plus_cli-0.0.1.dist-info/WHEEL
dagster_plus_cli-0.0.1.dist-info/top_level.txt
dagster_plus_cli-0.0.1.dist-info/RECORD
